wbck/__init__.py
wbck/load_config.py
wbck/repositories.py
wbck/runners.py
wbck/utils.py
wbck/sources/__init__.py
wbck/sources/aws.py
wbck/sources/base.py
wbck/sources/local.py
wbck-2.0.0.dist-info/LICENSE.md
wbck-2.0.0.dist-info/METADATA
wbck-2.0.0.dist-info/WHEEL
wbck-2.0.0.dist-info/entry_points.txt
wbck-2.0.0.dist-info/top_level.txt
wbck-2.0.0.dist-info/RECORD
