Metadata-Version: 2.1
Name: wbck
Version: 2.0.0
Summary: a command line utility to perform workspace backup
Home-page: https://github.com/argoyal/wbck.git
Author: Arpit Goyal
Author-email: arpitgoyal.iitkgp@outlook.com
License: UNKNOWN
Platform: UNKNOWN
Classifier: Programming Language :: Python :: 3
Classifier: Operating System :: OS Independent
Classifier: License :: OSI Approved :: MIT License
Requires-Python: >=3.6
Requires-Dist: boto3
